{
  "master": {
    "path": "versions/master",
    "name": "master",
    "sha": "8448e38f4090cc6f8db54538395460926ff30766",
    "tag": null
  },
  "v0.1.1": {
    "path": "versions/v0.1.1",
    "name": "v0.1.1",
    "sha": "0f1f7313860b50d65f40c1a2131bb532f4547f4b",
    "tag": "v0.1.1"
  },
  "-latest": {
    "path": "",
    "name": "Latest",
    "sha": "2be4b36d7519d504a4232daabda6e8132e59ef61",
    "tag": "v0.6.3"
  },
  "v0.1.2": {
    "path": "versions/v0.1.2",
    "name": "v0.1.2",
    "sha": "d7645a06523f14b380180d37dc11cc0129ee69f3",
    "tag": "v0.1.2"
  },
  "v0.2.0": {
    "path": "versions/v0.2.0",
    "name": "v0.2.0",
    "sha": "8657943ab49f3ca85fb16dd989d2384721b6d8ac",
    "tag": "v0.2.0"
  },
  "v0.2.1": {
    "path": "versions/v0.2.1",
    "name": "v0.2.1",
    "sha": "2759b5c49389cae1070305c1ec1865f978bee7fb",
    "tag": "v0.2.1"
  },
  "v0.2.2": {
    "path": "versions/v0.2.2",
    "name": "v0.2.2",
    "sha": "dc935016326f0560d72a8967f017f6fd32a73f98",
    "tag": "v0.2.2"
  },
  "v0.3.0": {
    "path": "versions/v0.3.0",
    "name": "v0.3.0",
    "sha": "98be45e8749ca731d39c5463aef0ddf059d33a5a",
    "tag": "v0.3.0"
  },
  "v0.3.1": {
    "path": "versions/v0.3.1",
    "name": "v0.3.1",
    "sha": "388d11476ffbf9f155bdae70b6729127f4d49204",
    "tag": "v0.3.1"
  },
  "v0.3.2": {
    "path": "versions/v0.3.2",
    "name": "v0.3.2",
    "sha": "2b9dbec6245a143bd09bfce9035e687c1dd64fdd",
    "tag": "v0.3.2"
  },
  "v0.3.3": {
    "path": "versions/v0.3.3",
    "name": "v0.3.3",
    "sha": "21dbbe3acd643b0b97e6145de52394ba1a80d814",
    "tag": "v0.3.3"
  },
  "v0.4.0": {
    "path": "versions/v0.4.0",
    "name": "v0.4.0",
    "sha": "313120b9593cfc7b16fb00c2d321a91b9da1de5e",
    "tag": "v0.4.0"
  },
  "v0.5.0": {
    "path": "versions/v0.5.0",
    "name": "v0.5.0",
    "sha": "46fe67ef6e212ae7f027241b042d4856aea181e2",
    "tag": "v0.5.0"
  },
  "v0.5.1": {
    "path": "versions/v0.5.1",
    "name": "v0.5.1",
    "sha": "ffb9fb34fbeb2e241f4997ba58f6d556f3962ae4",
    "tag": "v0.5.1"
  },
  "v0.5.3": {
    "path": "versions/v0.5.3",
    "name": "v0.5.3",
    "sha": "ef8a90ffec33d21e30cbaca03f332d2a16d2058b",
    "tag": "v0.5.3"
  },
  "v0.5.4": {
    "path": "versions/v0.5.4",
    "name": "v0.5.4",
    "sha": "04fc0568f880cd7c4910bcc7eb383a858b6761b2",
    "tag": "v0.5.4"
  },
  "v0.6.0": {
    "path": "versions/v0.6.0",
    "name": "v0.6.0",
    "sha": "dfc8cded0070eb54f081e6b82516ae438d4b5642",
    "tag": "v0.6.0"
  },
  "v0.6.1": {
    "path": "versions/v0.6.1",
    "name": "v0.6.1",
    "sha": "6c8af9cf4396d1cd5a1f126b28cb3a2b1eea1c5b",
    "tag": "v0.6.1"
  },
  "v0.6.2": {
    "path": "versions/v0.6.2",
    "name": "v0.6.2",
    "sha": "ec419e5e0eca376b6459b613a0a15cfc8ffd9177",
    "tag": "v0.6.2"
  },
  "v0.6.3": {
    "path": "versions/v0.6.3",
    "name": "v0.6.3",
    "sha": "2be4b36d7519d504a4232daabda6e8132e59ef61",
    "tag": "v0.6.3"
  }
}
